inked/__init__.py
inked/watermark.py
inked-0.1.3.dist-info/LICENSE
inked-0.1.3.dist-info/METADATA
inked-0.1.3.dist-info/WHEEL
inked-0.1.3.dist-info/entry_points.txt
inked-0.1.3.dist-info/top_level.txt
inked-0.1.3.dist-info/RECORD
