Metadata-Version: 2.1
Name: inked
Version: 0.1.3
Summary: A tool for adding text or image watermarks to images
Home-page: https://github.com/ksumesh21/inked
Author: Sumesh.K
Author-email: ksumesh21@gmail.com
License: UNKNOWN
Platform: UNKNOWN
Classifier: Programming Language :: Python :: 3
Classifier: License :: OSI Approved :: MIT License
Classifier: Operating System :: OS Independent
Requires-Python: >=3.8
License-File: LICENSE
Requires-Dist: Pillow>=8.0.0
